[
  {
    "name": "Reliance Petrochem Ltd",
    "sector": "Energy",
    "inspired_by": "Reliance",
    "market_cap": "Large",
    "current_price": 2002,
    "intrinsic_value": 2211,
    "pe": 17,
    "industry_pe": 24,
    "peg_ratio": 1.6,
    "roe": 26,
    "roce": 27,
    "debt_to_equity": 0.7,
    "interest_coverage": 5,
    "book_value": 789,
    "pb_ratio": 4,
    "dividend_yield": 2.5,
    "revenue_growth": 17,
    "profit_growth": 21,
    "profit_margin": 35,
    "working_capital_days": 76,
    "inventory_days": 23,
    "receivable_days": 31,
    "revenue_trend": "Improving",
    "profit_trend": "Improving",
    "roe_trend": "Improving",
    "debt_trend": "Declining",
    "margin_trend": "Improving"
  },
  {
    "name": "Coal India Energy",
    "sector": "Energy",
    "inspired_by": "Coal India",
    "market_cap": "Large",
    "current_price": 5261,
    "intrinsic_value": 92,
    "pe": 57,
    "industry_pe": 26,
    "peg_ratio": 4.7,
    "roe": 9,
    "roce": 9,
    "debt_to_equity": 1.1,
    "interest_coverage": 1,
    "book_value": 1497,
    "pb_ratio": 8.5,
    "dividend_yield": 1,
    "revenue_growth": 3,
    "profit_growth": 2,
    "profit_margin": 10,
    "working_capital_days": 74,
    "inventory_days": 39,
    "receivable_days": 43,
    "revenue_trend": "Volatile",
    "profit_trend": "Declining",
    "roe_trend": "Stable",
    "debt_trend": "High",
    "margin_trend": "Volatile"
  },
  {
    "name": "Oil & Natural Gas Corp",
    "sector": "Energy",
    "inspired_by": "ONGC",
    "market_cap": "Large",
    "current_price": 5904,
    "intrinsic_value": 5888,
    "pe": 28,
    "industry_pe": 24,
    "peg_ratio": 1.1,
    "roe": 26,
    "roce": 32,
    "debt_to_equity": 0.7,
    "interest_coverage": 6,
    "book_value": 1267,
    "pb_ratio": 2,
    "dividend_yield": 2.1,
    "revenue_growth": 24,
    "profit_growth": 27,
    "profit_margin": 17,
    "working_capital_days": 58,
    "inventory_days": 32,
    "receivable_days": 38,
    "revenue_trend": "Improving",
    "profit_trend": "Improving",
    "roe_trend": "Improving",
    "debt_trend": "Declining",
    "margin_trend": "Improving"
  },
  {
    "name": "Bharat Petroleum",
    "sector": "Energy",
    "inspired_by": "BPCL",
    "market_cap": "Large",
    "current_price": 7094,
    "intrinsic_value": 1887,
    "pe": 58,
    "industry_pe": 29,
    "peg_ratio": 4.1,
    "roe": 9,
    "roce": 7,
    "debt_to_equity": 0.8,
    "interest_coverage": 1,
    "book_value": 1611,
    "pb_ratio": 4.2,
    "dividend_yield": 2.4,
    "revenue_growth": 3,
    "profit_growth": -3,
    "profit_margin": 3,
    "working_capital_days": 38,
    "inventory_days": 58,
    "receivable_days": 40,
    "revenue_trend": "Volatile",
    "profit_trend": "Declining",
    "roe_trend": "Stable",
    "debt_trend": "High",
    "margin_trend": "Volatile"
  },
  {
    "name": "Adani Energy Grid",
    "sector": "Energy",
    "inspired_by": "Adani Green",
    "market_cap": "Large",
    "current_price": 536,
    "intrinsic_value": 7965,
    "pe": 24,
    "industry_pe": 25,
    "peg_ratio": 1,
    "roe": 29,
    "roce": 23,
    "debt_to_equity": 0,
    "interest_coverage": 4,
    "book_value": 757,
    "pb_ratio": 3.2,
    "dividend_yield": 2.6,
    "revenue_growth": 12,
    "profit_growth": 21,
    "profit_margin": 21,
    "working_capital_days": 61,
    "inventory_days": 24,
    "receivable_days": 30,
    "revenue_trend": "Improving",
    "profit_trend": "Improving",
    "roe_trend": "Improving",
    "debt_trend": "Declining",
    "margin_trend": "Improving"
  },
  {
    "name": "Tata Auto Works",
    "sector": "Auto",
    "inspired_by": "Tata Motors",
    "market_cap": "Large",
    "current_price": 6470,
    "intrinsic_value": 2076,
    "pe": 22,
    "industry_pe": 23,
    "peg_ratio": 1.1,
    "roe": 19,
    "roce": 18,
    "debt_to_equity": 0.5,
    "interest_coverage": 14,
    "book_value": 232,
    "pb_ratio": 5,
    "dividend_yield": 0.6,
    "revenue_growth": 23,
    "profit_growth": 14,
    "profit_margin": 25,
    "working_capital_days": 35,
    "inventory_days": 55,
    "receivable_days": 42,
    "revenue_trend": "Improving",
    "profit_trend": "Improving",
    "roe_trend": "Improving",
    "debt_trend": "Declining",
    "margin_trend": "Improving"
  },
  {
    "name": "Maruti Auto India",
    "sector": "Auto",
    "inspired_by": "Maruti Suzuki",
    "market_cap": "Large",
    "current_price": 899,
    "intrinsic_value": 2683,
    "pe": 75,
    "industry_pe": 30,
    "peg_ratio": 2.1,
    "roe": 11,
    "roce": 7,
    "debt_to_equity": 0.4,
    "interest_coverage": 3,
    "book_value": 1955,
    "pb_ratio": 6.1,
    "dividend_yield": 1.3,
    "revenue_growth": 0,
    "profit_growth": 0,
    "profit_margin": 6,
    "working_capital_days": 78,
    "inventory_days": 47,
    "receivable_days": 38,
    "revenue_trend": "Volatile",
    "profit_trend": "Declining",
    "roe_trend": "Stable",
    "debt_trend": "High",
    "margin_trend": "Volatile"
  },
  {
    "name": "Mahindra Vehicles",
    "sector": "Auto",
    "inspired_by": "M&M",
    "market_cap": "Large",
    "current_price": 6209,
    "intrinsic_value": 7866,
    "pe": 26,
    "industry_pe": 27,
    "peg_ratio": 1.6,
    "roe": 26,
    "roce": 16,
    "debt_to_equity": 0.6,
    "interest_coverage": 9,
    "book_value": 1470,
    "pb_ratio": 1.8,
    "dividend_yield": 0.3,
    "revenue_growth": 24,
    "profit_growth": 26,
    "profit_margin": 32,
    "working_capital_days": 34,
    "inventory_days": 24,
    "receivable_days": 17,
    "revenue_trend": "Improving",
    "profit_trend": "Improving",
    "roe_trend": "Improving",
    "debt_trend": "Declining",
    "margin_trend": "Improving"
  },
  {
    "name": "Bajaj Two Wheeler",
    "sector": "Auto",
    "inspired_by": "Bajaj Auto",
    "market_cap": "Large",
    "current_price": 4254,
    "intrinsic_value": 2198,
    "pe": 54,
    "industry_pe": 30,
    "peg_ratio": 4.6,
    "roe": 5,
    "roce": 9,
    "debt_to_equity": 1.2,
    "interest_coverage": 3,
    "book_value": 400,
    "pb_ratio": 5,
    "dividend_yield": 1.5,
    "revenue_growth": 6,
    "profit_growth": -2,
    "profit_margin": 8,
    "working_capital_days": 43,
    "inventory_days": 60,
    "receivable_days": 11,
    "revenue_trend": "Volatile",
    "profit_trend": "Declining",
    "roe_trend": "Stable",
    "debt_trend": "High",
    "margin_trend": "Volatile"
  },
  {
    "name": "Eicher Trucks",
    "sector": "Auto",
    "inspired_by": "Eicher Motors",
    "market_cap": "Large",
    "current_price": 7724,
    "intrinsic_value": 1947,
    "pe": 21,
    "industry_pe": 33,
    "peg_ratio": 0.9,
    "roe": 31,
    "roce": 26,
    "debt_to_equity": 0.5,
    "interest_coverage": 6,
    "book_value": 202,
    "pb_ratio": 2.9,
    "dividend_yield": 2.6,
    "revenue_growth": 21,
    "profit_growth": 30,
    "profit_margin": 33,
    "working_capital_days": 42,
    "inventory_days": 0,
    "receivable_days": 18,
    "revenue_trend": "Improving",
    "profit_trend": "Improving",
    "roe_trend": "Improving",
    "debt_trend": "Declining",
    "margin_trend": "Improving"
  },
  {
    "name": "HDFC Finance Corp",
    "sector": "Banking",
    "inspired_by": "HDFC Bank",
    "market_cap": "Large",
    "current_price": 2612,
    "intrinsic_value": 7198,
    "pe": 19,
    "industry_pe": 23,
    "peg_ratio": 0.6,
    "roe": 35,
    "roce": 29,
    "debt_to_equity": 0.1,
    "interest_coverage": 10,
    "book_value": 1057,
    "pb_ratio": 4.5,
    "dividend_yield": 1.4,
    "revenue_growth": 17,
    "profit_growth": 21,
    "profit_margin": 18,
    "working_capital_days": 10,
    "inventory_days": 29,
    "receivable_days": 48,
    "revenue_trend": "Improving",
    "profit_trend": "Improving",
    "roe_trend": "Improving",
    "debt_trend": "Declining",
    "margin_trend": "Improving"
  },
  {
    "name": "ICICI Bank Ltd",
    "sector": "Banking",
    "inspired_by": "ICICI Bank",
    "market_cap": "Large",
    "current_price": 3862,
    "intrinsic_value": 989,
    "pe": 76,
    "industry_pe": 28,
    "peg_ratio": 4,
    "roe": 7,
    "roce": 12,
    "debt_to_equity": 1.4,
    "interest_coverage": 2,
    "book_value": 1012,
    "pb_ratio": 8.9,
    "dividend_yield": 1,
    "revenue_growth": 6,
    "profit_growth": 2,
    "profit_margin": 2,
    "working_capital_days": 66,
    "inventory_days": 43,
    "receivable_days": 29,
    "revenue_trend": "Volatile",
    "profit_trend": "Declining",
    "roe_trend": "Stable",
    "debt_trend": "High",
    "margin_trend": "Volatile"
  },
  {
    "name": "State Bank India",
    "sector": "Banking",
    "inspired_by": "SBI",
    "market_cap": "Large",
    "current_price": 1622,
    "intrinsic_value": 2418,
    "pe": 29,
    "industry_pe": 34,
    "peg_ratio": 1.9,
    "roe": 34,
    "roce": 16,
    "debt_to_equity": 0.5,
    "interest_coverage": 8,
    "book_value": 366,
    "pb_ratio": 5.5,
    "dividend_yield": 2.8,
    "revenue_growth": 23,
    "profit_growth": 20,
    "profit_margin": 21,
    "working_capital_days": 38,
    "inventory_days": 20,
    "receivable_days": 34,
    "revenue_trend": "Improving",
    "profit_trend": "Improving",
    "roe_trend": "Improving",
    "debt_trend": "Declining",
    "margin_trend": "Improving"
  },
  {
    "name": "Axis Fin Bank",
    "sector": "Banking",
    "inspired_by": "Axis Bank",
    "market_cap": "Large",
    "current_price": 2944,
    "intrinsic_value": 2106,
    "pe": 65,
    "industry_pe": 29,
    "peg_ratio": 4.9,
    "roe": 12,
    "roce": 11,
    "debt_to_equity": 1.5,
    "interest_coverage": 3,
    "book_value": 912,
    "pb_ratio": 1.2,
    "dividend_yield": 1.9,
    "revenue_growth": 6,
    "profit_growth": 0,
    "profit_margin": 10,
    "working_capital_days": 68,
    "inventory_days": 13,
    "receivable_days": 57,
    "revenue_trend": "Volatile",
    "profit_trend": "Declining",
    "roe_trend": "Stable",
    "debt_trend": "High",
    "margin_trend": "Volatile"
  },
  {
    "name": "Kotak Finance",
    "sector": "Banking",
    "inspired_by": "Kotak Mahindra",
    "market_cap": "Large",
    "current_price": 7068,
    "intrinsic_value": 3167,
    "pe": 22,
    "industry_pe": 23,
    "peg_ratio": 2,
    "roe": 21,
    "roce": 20,
    "debt_to_equity": 0,
    "interest_coverage": 9,
    "book_value": 1603,
    "pb_ratio": 4.3,
    "dividend_yield": 1.6,
    "revenue_growth": 15,
    "profit_growth": 25,
    "profit_margin": 35,
    "working_capital_days": 14,
    "inventory_days": 2,
    "receivable_days": 11,
    "revenue_trend": "Improving",
    "profit_trend": "Improving",
    "roe_trend": "Improving",
    "debt_trend": "Declining",
    "margin_trend": "Improving"
  },
  {
    "name": "Infosys Digital Ltd",
    "sector": "IT",
    "inspired_by": "Infosys",
    "market_cap": "Large",
    "current_price": 3565,
    "intrinsic_value": 7101,
    "pe": 24,
    "industry_pe": 34,
    "peg_ratio": 0.8,
    "roe": 27,
    "roce": 25,
    "debt_to_equity": 0.5,
    "interest_coverage": 15,
    "book_value": 1950,
    "pb_ratio": 5,
    "dividend_yield": 3,
    "revenue_growth": 14,
    "profit_growth": 23,
    "profit_margin": 16,
    "working_capital_days": 40,
    "inventory_days": 11,
    "receivable_days": 37,
    "revenue_trend": "Improving",
    "profit_trend": "Improving",
    "roe_trend": "Improving",
    "debt_trend": "Declining",
    "margin_trend": "Improving"
  },
  {
    "name": "TCS Software Services",
    "sector": "IT",
    "inspired_by": "TCS",
    "market_cap": "Large",
    "current_price": 7563,
    "intrinsic_value": 600,
    "pe": 59,
    "industry_pe": 26,
    "peg_ratio": 2.9,
    "roe": 10,
    "roce": 10,
    "debt_to_equity": 2.6,
    "interest_coverage": 3,
    "book_value": 1589,
    "pb_ratio": 3.2,
    "dividend_yield": 2.2,
    "revenue_growth": 3,
    "profit_growth": 5,
    "profit_margin": 8,
    "working_capital_days": 10,
    "inventory_days": 59,
    "receivable_days": 38,
    "revenue_trend": "Volatile",
    "profit_trend": "Declining",
    "roe_trend": "Stable",
    "debt_trend": "High",
    "margin_trend": "Volatile"
  },
  {
    "name": "Wipro Tech",
    "sector": "IT",
    "inspired_by": "Wipro",
    "market_cap": "Large",
    "current_price": 1101,
    "intrinsic_value": 5450,
    "pe": 28,
    "industry_pe": 28,
    "peg_ratio": 1.2,
    "roe": 34,
    "roce": 33,
    "debt_to_equity": 0,
    "interest_coverage": 13,
    "book_value": 1908,
    "pb_ratio": 8,
    "dividend_yield": 1.5,
    "revenue_growth": 11,
    "profit_growth": 25,
    "profit_margin": 15,
    "working_capital_days": 83,
    "inventory_days": 23,
    "receivable_days": 46,
    "revenue_trend": "Improving",
    "profit_trend": "Improving",
    "roe_trend": "Improving",
    "debt_trend": "Declining",
    "margin_trend": "Improving"
  },
  {
    "name": "HCL Technologies",
    "sector": "IT",
    "inspired_by": "HCL",
    "market_cap": "Large",
    "current_price": 3382,
    "intrinsic_value": 1006,
    "pe": 40,
    "industry_pe": 23,
    "peg_ratio": 3.9,
    "roe": 12,
    "roce": 8,
    "debt_to_equity": 1,
    "interest_coverage": 3,
    "book_value": 1502,
    "pb_ratio": 7.9,
    "dividend_yield": 0.6,
    "revenue_growth": 8,
    "profit_growth": -2,
    "profit_margin": 8,
    "working_capital_days": 86,
    "inventory_days": 11,
    "receivable_days": 47,
    "revenue_trend": "Volatile",
    "profit_trend": "Declining",
    "roe_trend": "Stable",
    "debt_trend": "High",
    "margin_trend": "Volatile"
  },
  {
    "name": "Tech Mahindra Ltd",
    "sector": "IT",
    "inspired_by": "Tech Mahindra",
    "market_cap": "Large",
    "current_price": 1122,
    "intrinsic_value": 8043,
    "pe": 19,
    "industry_pe": 30,
    "peg_ratio": 0.5,
    "roe": 18,
    "roce": 35,
    "debt_to_equity": 0.2,
    "interest_coverage": 8,
    "book_value": 266,
    "pb_ratio": 3.9,
    "dividend_yield": 0.9,
    "revenue_growth": 17,
    "profit_growth": 13,
    "profit_margin": 27,
    "working_capital_days": 27,
    "inventory_days": 20,
    "receivable_days": 12,
    "revenue_trend": "Improving",
    "profit_trend": "Improving",
    "roe_trend": "Improving",
    "debt_trend": "Declining",
    "margin_trend": "Improving"
  },
  {
    "name": "ITC Consumer Ltd",
    "sector": "FMCG",
    "inspired_by": "ITC",
    "market_cap": "Large",
    "current_price": 4292,
    "intrinsic_value": 7979,
    "pe": 19,
    "industry_pe": 28,
    "peg_ratio": 0.8,
    "roe": 24,
    "roce": 22,
    "debt_to_equity": 0.4,
    "interest_coverage": 12,
    "book_value": 865,
    "pb_ratio": 7.7,
    "dividend_yield": 0.2,
    "revenue_growth": 12,
    "profit_growth": 22,
    "profit_margin": 31,
    "working_capital_days": 27,
    "inventory_days": 14,
    "receivable_days": 20,
    "revenue_trend": "Improving",
    "profit_trend": "Improving",
    "roe_trend": "Improving",
    "debt_trend": "Declining",
    "margin_trend": "Improving"
  },
  {
    "name": "Hindustan Unilever",
    "sector": "FMCG",
    "inspired_by": "HUL",
    "market_cap": "Large",
    "current_price": 7758,
    "intrinsic_value": 3867,
    "pe": 50,
    "industry_pe": 23,
    "peg_ratio": 2.4,
    "roe": 6,
    "roce": 11,
    "debt_to_equity": 2,
    "interest_coverage": 1,
    "book_value": 1219,
    "pb_ratio": 5.6,
    "dividend_yield": 2.9,
    "revenue_growth": 2,
    "profit_growth": 3,
    "profit_margin": 10,
    "working_capital_days": 87,
    "inventory_days": 34,
    "receivable_days": 25,
    "revenue_trend": "Volatile",
    "profit_trend": "Declining",
    "roe_trend": "Stable",
    "debt_trend": "High",
    "margin_trend": "Volatile"
  },
  {
    "name": "Nestle India",
    "sector": "FMCG",
    "inspired_by": "Nestle",
    "market_cap": "Large",
    "current_price": 6977,
    "intrinsic_value": 4327,
    "pe": 20,
    "industry_pe": 21,
    "peg_ratio": 0.6,
    "roe": 25,
    "roce": 31,
    "debt_to_equity": 0.2,
    "interest_coverage": 6,
    "book_value": 619,
    "pb_ratio": 1.8,
    "dividend_yield": 2.2,
    "revenue_growth": 23,
    "profit_growth": 28,
    "profit_margin": 17,
    "working_capital_days": 88,
    "inventory_days": 45,
    "receivable_days": 30,
    "revenue_trend": "Improving",
    "profit_trend": "Improving",
    "roe_trend": "Improving",
    "debt_trend": "Declining",
    "margin_trend": "Improving"
  },
  {
    "name": "Britannia Foods",
    "sector": "FMCG",
    "inspired_by": "Britannia",
    "market_cap": "Large",
    "current_price": 4803,
    "intrinsic_value": 536,
    "pe": 52,
    "industry_pe": 33,
    "peg_ratio": 2.7,
    "roe": 6,
    "roce": 11,
    "debt_to_equity": 1.2,
    "interest_coverage": 1,
    "book_value": 595,
    "pb_ratio": 2.3,
    "dividend_yield": 1.8,
    "revenue_growth": 4,
    "profit_growth": -4,
    "profit_margin": 5,
    "working_capital_days": 65,
    "inventory_days": 27,
    "receivable_days": 49,
    "revenue_trend": "Volatile",
    "profit_trend": "Declining",
    "roe_trend": "Stable",
    "debt_trend": "High",
    "margin_trend": "Volatile"
  },
  {
    "name": "Dabur Ayurveda",
    "sector": "FMCG",
    "inspired_by": "Dabur",
    "market_cap": "Large",
    "current_price": 4700,
    "intrinsic_value": 5617,
    "pe": 25,
    "industry_pe": 26,
    "peg_ratio": 0.8,
    "roe": 15,
    "roce": 17,
    "debt_to_equity": 0.4,
    "interest_coverage": 9,
    "book_value": 1407,
    "pb_ratio": 7.2,
    "dividend_yield": 2.8,
    "revenue_growth": 21,
    "profit_growth": 20,
    "profit_margin": 32,
    "working_capital_days": 21,
    "inventory_days": 34,
    "receivable_days": 32,
    "revenue_trend": "Improving",
    "profit_trend": "Improving",
    "roe_trend": "Improving",
    "debt_trend": "Declining",
    "margin_trend": "Improving"
  },
  {
    "name": "Sun Pharma Labs",
    "sector": "Pharma",
    "inspired_by": "Sun Pharma",
    "market_cap": "Large",
    "current_price": 1606,
    "intrinsic_value": 3168,
    "pe": 18,
    "industry_pe": 21,
    "peg_ratio": 1,
    "roe": 16,
    "roce": 27,
    "debt_to_equity": 0.6,
    "interest_coverage": 5,
    "book_value": 1236,
    "pb_ratio": 2.3,
    "dividend_yield": 2.2,
    "revenue_growth": 17,
    "profit_growth": 12,
    "profit_margin": 19,
    "working_capital_days": 62,
    "inventory_days": 18,
    "receivable_days": 49,
    "revenue_trend": "Improving",
    "profit_trend": "Improving",
    "roe_trend": "Improving",
    "debt_trend": "Declining",
    "margin_trend": "Improving"
  },
  {
    "name": "Dr Reddy Therapeutics",
    "sector": "Pharma",
    "inspired_by": "Dr Reddy's",
    "market_cap": "Large",
    "current_price": 4527,
    "intrinsic_value": 1886,
    "pe": 77,
    "industry_pe": 33,
    "peg_ratio": 3.5,
    "roe": 9,
    "roce": 10,
    "debt_to_equity": 1.9,
    "interest_coverage": 3,
    "book_value": 1708,
    "pb_ratio": 3.7,
    "dividend_yield": 2.6,
    "revenue_growth": 5,
    "profit_growth": 5,
    "profit_margin": 6,
    "working_capital_days": 48,
    "inventory_days": 39,
    "receivable_days": 60,
    "revenue_trend": "Volatile",
    "profit_trend": "Declining",
    "roe_trend": "Stable",
    "debt_trend": "High",
    "margin_trend": "Volatile"
  },
  {
    "name": "Cipla Healthcare",
    "sector": "Pharma",
    "inspired_by": "Cipla",
    "market_cap": "Large",
    "current_price": 5363,
    "intrinsic_value": 2894,
    "pe": 22,
    "industry_pe": 30,
    "peg_ratio": 1.3,
    "roe": 20,
    "roce": 21,
    "debt_to_equity": 0.6,
    "interest_coverage": 4,
    "book_value": 1883,
    "pb_ratio": 5.2,
    "dividend_yield": 2.4,
    "revenue_growth": 15,
    "profit_growth": 28,
    "profit_margin": 25,
    "working_capital_days": 49,
    "inventory_days": 40,
    "receivable_days": 39,
    "revenue_trend": "Improving",
    "profit_trend": "Improving",
    "roe_trend": "Improving",
    "debt_trend": "Declining",
    "margin_trend": "Improving"
  },
  {
    "name": "Divis Laboratories",
    "sector": "Pharma",
    "inspired_by": "Divis Labs",
    "market_cap": "Large",
    "current_price": 293,
    "intrinsic_value": 1538,
    "pe": 97,
    "industry_pe": 34,
    "peg_ratio": 3.2,
    "roe": 6,
    "roce": 10,
    "debt_to_equity": 1.7,
    "interest_coverage": 2,
    "book_value": 1772,
    "pb_ratio": 1,
    "dividend_yield": 1,
    "revenue_growth": 3,
    "profit_growth": 3,
    "profit_margin": 8,
    "working_capital_days": 68,
    "inventory_days": 44,
    "receivable_days": 48,
    "revenue_trend": "Volatile",
    "profit_trend": "Declining",
    "roe_trend": "Stable",
    "debt_trend": "High",
    "margin_trend": "Volatile"
  },
  {
    "name": "Lupin Pharma",
    "sector": "Pharma",
    "inspired_by": "Lupin",
    "market_cap": "Large",
    "current_price": 87,
    "intrinsic_value": 1003,
    "pe": 26,
    "industry_pe": 35,
    "peg_ratio": 1.9,
    "roe": 28,
    "roce": 27,
    "debt_to_equity": 0.4,
    "interest_coverage": 9,
    "book_value": 392,
    "pb_ratio": 8.4,
    "dividend_yield": 1.6,
    "revenue_growth": 18,
    "profit_growth": 12,
    "profit_margin": 34,
    "working_capital_days": 68,
    "inventory_days": 0,
    "receivable_days": 28,
    "revenue_trend": "Improving",
    "profit_trend": "Improving",
    "roe_trend": "Improving",
    "debt_trend": "Declining",
    "margin_trend": "Improving"
  }
]